saudi_dialect_eou/__init__.py
saudi_dialect_eou/arabic_model.py
saudi_dialect_eou/log.py
saudi_dialect_eou/version.py
saudi_dialect_eou-0.1.0.dist-info/METADATA
saudi_dialect_eou-0.1.0.dist-info/WHEEL
saudi_dialect_eou-0.1.0.dist-info/top_level.txt
saudi_dialect_eou-0.1.0.dist-info/RECORD
