Metadata-Version: 2.4
Name: saudi-dialect-eou
Version: 0.1.0
Summary: Arabic End-of-Utterance detection plugin for LiveKit Agents - Saudi dialect optimized
Author: Salma Mohammed Hamed
License: Apache-2.0
Keywords: livekit,agents,arabic,eou,turn-detection,voice-ai
Classifier: Development Status :: 4 - Beta
Classifier: Intended Audience :: Developers
Classifier: License :: OSI Approved :: Apache Software License
Classifier: Programming Language :: Python :: 3
Classifier: Programming Language :: Python :: 3.9
Classifier: Programming Language :: Python :: 3.10
Classifier: Programming Language :: Python :: 3.11
Classifier: Programming Language :: Python :: 3.12
Classifier: Topic :: Multimedia :: Sound/Audio
Classifier: Topic :: Scientific/Engineering :: Artificial Intelligence
Requires-Python: >=3.9
Requires-Dist: livekit-agents>=1.0.0
Requires-Dist: transformers>=4.35.0
Requires-Dist: torch>=2.0.0
Provides-Extra: dev
Requires-Dist: pytest>=7.0.0; extra == "dev"
Requires-Dist: black>=23.0.0; extra == "dev"
Requires-Dist: mypy>=1.0.0; extra == "dev"
